donutllmtools.py
Donut_LLM_Tools-24.5.29.dist-info/LICENSE
Donut_LLM_Tools-24.5.29.dist-info/METADATA
Donut_LLM_Tools-24.5.29.dist-info/WHEEL
Donut_LLM_Tools-24.5.29.dist-info/top_level.txt
Donut_LLM_Tools-24.5.29.dist-info/RECORD
