Metadata-Version: 2.1
Name: Donut-LLM-Tools
Version: 24.5.29
Summary: Tools for creating datasets, training and loading AI models
Home-page: https://github.com/gauthamnair2005/donut-llm-tools
Author: Gautham Nair
Author-email: gautham.nair.2005@gmail.com
License: MIT License
Keywords: AI,ML,Train,Model,Dataset
Classifier: License :: OSI Approved :: MIT License
Classifier: Programming Language :: Python :: 3
Requires-Python: <3.12,>=3.9
License-File: LICENSE
Requires-Dist: DonutLLMCore
Requires-Dist: wikipedia
Provides-Extra: dev
Requires-Dist: black ; extra == 'dev'
Requires-Dist: bumpver ; extra == 'dev'
Requires-Dist: isort ; extra == 'dev'
Requires-Dist: pip-tools ; extra == 'dev'
Requires-Dist: pytest ; extra == 'dev'
